f3dasm_simulate/__init__.py
f3dasm_simulate/abaqus/__init__.py
f3dasm_simulate/abaqus/amplitudesampler.py
f3dasm_simulate/abaqus/cddm.py
f3dasm_simulate/abaqus/circle_particles.py
f3dasm_simulate/abaqus/loading.py
f3dasm_simulate/abaqus/material.py
f3dasm_simulate/abaqus/microstructure.py
f3dasm_simulate/abaqus/microstructure_generator.py
f3dasm_simulate/abaqus/overwrite_inputs.py
f3dasm_simulate/abaqus/simulator.py
f3dasm_simulate/abaqus/simulator_assertinputs.py
f3dasm_simulate/abaqus/simulator_info.py
f3dasm_simulate/abaqus/simulator_part.py
f3dasm_simulate/abaqus/sphere_particles.py
f3dasm_simulate/abaqus/utils.py
f3dasm_simulate/abaqus/scriptbase/__init__.py
f3dasm_simulate/abaqus/scriptbase/basic_analysis_scripts/__init__.py
f3dasm_simulate/abaqus/scriptbase/basic_analysis_scripts/common_procedure.py
f3dasm_simulate/abaqus/scriptbase/basic_analysis_scripts/geometry_modeling.py
f3dasm_simulate/abaqus/scriptbase/basic_analysis_scripts/jobs.py
f3dasm_simulate/abaqus/scriptbase/basic_analysis_scripts/loading_condition.py
f3dasm_simulate/abaqus/scriptbase/basic_analysis_scripts/materials.py
f3dasm_simulate/abaqus/scriptbase/basic_analysis_scripts/mesh.py
f3dasm_simulate/abaqus/scriptbase/basic_analysis_scripts/periodical_boundary_condition.py
f3dasm_simulate/abaqus/scriptbase/basic_analysis_scripts/post_process.py
f3dasm_simulate/abaqus/scriptbase/basic_analysis_scripts/steps.py
f3dasm_simulate/abaqus/scriptbase/benchmark_abaqus_scripts/__init__.py
f3dasm_simulate/abaqus/scriptbase/benchmark_abaqus_scripts/hollow_plate_sve.py
f3dasm_simulate/abaqus/scriptbase/benchmark_abaqus_scripts/single_material_sve.py
f3dasm_simulate/abaqus/scriptbase/benchmark_abaqus_scripts/two_materials_rve.py
f3dasm_simulate/abaqus/scriptbase/benchmark_abaqus_scripts/two_materials_sve.py
f3dasm_simulate/abaqus/scriptbase/benchmark_abaqus_scripts/veni_rve.py
f3dasm_simulate-1.1.0.dist-info/METADATA
f3dasm_simulate-1.1.0.dist-info/WHEEL
f3dasm_simulate-1.1.0.dist-info/top_level.txt
f3dasm_simulate-1.1.0.dist-info/RECORD
