Metadata-Version: 2.1
Name: f3dasm-simulate
Version: 1.1.0
Summary: f3dasm_simulate: Simulation extension for f3dasm
Home-page: https://github.com/bessagroup/f3dasm_simulate
Author: Martin van der Schelling
Author-email: M.P.vanderSchelling@tudelft.nl
License: BSD-3-Clause License
Keywords: keyword1,keyword2,keyword3
Classifier: Development Status :: 5 - Production/Stable
Classifier: Intended Audience :: Science/Research
Classifier: Topic :: Scientific/Engineering
Classifier: Topic :: Scientific/Engineering :: Artificial Intelligence
Classifier: Topic :: Scientific/Engineering :: Physics
Classifier: License :: OSI Approved :: BSD License
Classifier: Natural Language :: English
Classifier: Programming Language :: Python :: 3
Requires-Python: >=3.8
Requires-Dist: f3dasm >=1.3.1
